Metadata-Version: 2.1
Name: dataengtoolbox
Version: 0.3.0
Summary: Data Engineering Toolbox
Home-page: UNKNOWN
Author: ITESO MAF - Data Engineering Course
License: UNKNOWN
Platform: UNKNOWN
Requires-Python: >=3.8.10
